[
{
  "id": "001",
  "titulo": "Apartamento moderno com vista para o parque",
  "quartos": 2,
  "quartos_complemento": "com suíte",
  "banheiros": 1,
  "banheiros_complemento": "com box de vidro",
  "vagas": 2,
  "vagas_complemento": "cobertas",
  "metragem": 36,
  "metragem_complemento": "Área útil",
  "sol": "Sol da manhã",
  "sol_complemento": "na sala e varanda",
  "preco_complemento": "à vista",
    "imagem": "images/poa/722585/1.jpg",
    "imagens": [
      "images/poa/722585/2.jpg",
      "images/poa/722585/3.jpg",
      "images/poa/722585/4.jpg",
      "images/poa/722585/5.jpg"
    ],
    "descricao": "Excelente apartamento 1 dormitório, ideal para estudantes e pronto para morar!",
    "link": "imovel.html?id=722585",
    "mensagem_whats": "Oi! Vi esse imóvel no Portal de Investimento e achei interessante. Pode me passar mais detalhes? Código: [722585]",
    "regiao": "Porto Alegre",
    "tipo": "Apartamento",
    "preco": 245000,
    "whatsapp": "555135731139"
  },
  {
    "id": "373589",
    "titulo": "Apartamento à Venda - 2 Dormitórios Impecavelmente Decorado",
    "quartos": 2,
    "quartos_complemento": "com suíte",
    "banheiros": 1,
    "banheiros_complemento": "com box de vidro",
    "vagas": 2,
    "vagas_complemento": "cobertas",
    "metragem": 36,
    "metragem_complemento": "Área útil",
    "sol": "Sol da manhã",
    "sol_complemento": "na sala e varanda",
    "preco_complemento": "à vista",
    "imagem": "images/poa/373589/1.jpg",
    "imagens": [
      "images/poa/373589/2.jpg",
      "images/poa/373589/3.jpg",
      "images/poa/373589/4.jpg",
      "images/poa/373589/5.jpg",
      "images/poa/373589/6.jpg",
      "images/poa/373589/7.jpg",
      "images/poa/373589/8.jpg",
      "images/poa/373589/9.jpg",
      "images/poa/373589/10.jpg",
      "images/poa/373589/11.jpg",
      "images/poa/373589/12.jpg"
    ],
    "descricao": "Descubra o seu novo lar! Este apartamento é uma verdadeira obra-prima, projetada por arquiteto, com: 2 dormitórios, sendo 1 suíte, amplo living com 2 ambientes, ideal para receber amigos e familiares.  Cozinha americana moderna, equipada com churrasqueira e área de serviço integrada. Banheiro social e ampla sacada, perfeita para relaxar com vista lateral para o Guaíba, onde você pode admirar um deslumbrante pôr do sol,  2 vagas de garagem incluídas",
    "link": "imovel.html?id=373589",
    "mensagem_whats": "Oi! Vi esse imóvel no Portal de Investimento e achei interessante. Pode me passar mais detalhes? Código: [373589]",
    "regiao": "Porto Alegre",
    "tipo": "Apartamento",
    "preco": 879000,
    "whatsapp": "555135731139"
  },
  {
    "id": "214515",
    "titulo": "Apartamento Semi mobiliado   02 quartos, sendo 01 suíte",
    "quartos": 2,
    "quartos_complemento": "com suíte",
    "banheiros": 1,
    "banheiros_complemento": "com box de vidro",
    "vagas": 2,
    "vagas_complemento": "cobertas",
    "metragem": 36,
    "metragem_complemento": "Área útil",
    "sol": "Sol da manhã",
    "sol_complemento": "na sala e varanda",
    "preco_complemento": "à vista",
    "imagem": "images/poa/214515/1.jpg",
    "imagens": [
      "images/poa/214515/2.jpg",
      "images/poa/214515/3.jpg",
      "images/poa/214515/4.jpg",
      "images/poa/214515/5.jpg",
      "images/poa/214515/6.jpg",
      "images/poa/214515/7.jpg",
      "images/poa/214515/8.jpg",
      "images/poa/214515/9.jpg",
      "images/poa/214515/10.jpg",
      "images/poa/214515/11.jpg",
      "images/poa/214515/12.jpg"
    ],
    "descricao": "Condomínio com infraestrutura completa: piscina aquecida, salão de festas, espaço gourmet, fitness, salão de jogos, playground, portaria 24 horas.",
    "link": "imovel.html?id=214515",
    "mensagem_whats": "Oi! Vi esse imóvel no Portal de Investimento e achei interessante. Pode me passar mais detalhes? Código: [214515]",
    "regiao": "Porto Alegre",
    "tipo": "Apartamento",
    "preco": 589000,
    "whatsapp": "555135731139"
  },
  {
    "id": "716113",
    "titulo": "Um apartamento pra quem não quer só morar, quer viver bem",
    "quartos": 2,
    "quartos_complemento": "com suíte",
    "banheiros": 2,
    "banheiros_complemento": "com box de vidro",
    "vagas": 2,
    "vagas_complemento": "cobertas",
    "metragem": 89,
    "metragem_complemento": "Área útil",
    "sol": "Sol da manhã",
    "sol_complemento": "na sala e varanda",
    "preco_complemento": "à vista",
    "imagem": "images/poa/716113/1.jpg",
    "imagens": [
      "images/poa/716113/3.jpg",
      "images/poa/716113/4.jpg",
      "images/poa/716113/5.jpg",
      "images/poa/716113/6.jpg",
      "images/poa/716113/7.jpg",
      "images/poa/716113/8.jpg",
      "images/poa/716113/9.jpg",
      "images/poa/716113/10.jpg",
      "images/poa/716113/11.jpg",
      "images/poa/716113/12.jpg"
    ],
    "descricao": "Na Carlos von Koseritz, no Higienópolis, esse apê foi pensado nos detalhes: suíte com closet e sacada, vista de tirar o fôlego, cozinha com churrasqueira integrada e uma sala com aquele janelão que entrega o sol perfeito. Mobiliado, decorado, com mais de R$ 200 mil investidos em móveis e eletros ? é entrar e viver. O ambiente fala: em cada canto, a harmonia entre design e iluminação. A climatização, o convida a desacelerar e simplesmente estar.",
    "link": "imovel.html?id=716113",
    "mensagem_whats": "Oi! Vi esse imóvel no Portal de Investimento e achei interessante. Pode me passar mais detalhes? Código: [716113]",
    "regiao": "Porto Alegre",
    "tipo": "Apartamento",
    "preco": 949000,
    "whatsapp": "555135731139"
  }
  
]
