[
  {
    "id": "lanc001",
    "titulo": "Residencial Vista Verde",
    "regiao": "Canoas",
    "agencia": "Canoas - Jardim do Lago",
    "tipo": "Apartamento",
    "imagem": "images/jardim do lago.jpg",
    "imagens": [
      "images/jardim do lago.jpg",
      "images/jardim do lago.jpg",
      "images/jardim do lago.jpg"
    ],
    "descricao": "Lançamento exclusivo com área de lazer completa, localização privilegiada e acabamento de alto padrão. Próximo a escolas, supermercados e principais vias de acesso.",
    "metragem": 85,
    "metragem_min": 65,
    "metragem_max": 120,
    "metragem_complemento": "Área privativa",
    "quartos": 3,
    "quartos_min": 2,
    "quartos_max": 3,
    "quartos_complemento": "Suíte master",
    "banheiros": 2,
    "banheiros_complemento": "Sociais",
    "vagas": 2,
    "vagas_complemento": "Cobertas",
    "sol": "Nascente",
    "sol_complemento": "Sol da manhã",
    "preco": 450000,
    "preco_complemento": "Consulte condições especiais",
    "status": "Em lançamento",
    "previsao_entrega": "Dez/2026",
    "destaque": true,
    "whatsapp": "5551993303583",
    "mensagem_whats": "Olá! Vi o lançamento Residencial Vista Verde no Portal de Investimento e gostaria de mais informações."
  },
  {
    "id": "lanc002",
    "titulo": "Edifício Horizonte Premium",
    "regiao": "Porto Alegre",
    "agencia": "Moinhos de Vento",
    "tipo": "Apartamento Alto Padrão",
    "imagem": "images/moinhos.jpg",
    "imagens": [
      "images/moinhos.jpg",
      "images/moinhos.jpg",
      "images/moinhos.jpg"
    ],
    "descricao": "Empreendimento de luxo na região mais valorizada de Porto Alegre. Vista panorâmica, 4 suítes, pé-direito duplo e acabamento premium.",
    "metragem": 180,
    "metragem_min": 150,
    "metragem_max": 250,
    "metragem_complemento": "Área privativa",
    "quartos": 4,
    "quartos_min": 3,
    "quartos_max": 4,
    "quartos_complemento": "Todas suítes",
    "banheiros": 5,
    "banheiros_complemento": "Suítes + lavabo",
    "vagas": 3,
    "vagas_complemento": "Box privativos",
    "sol": "Norte",
    "sol_complemento": "Sol o dia todo",
    "preco": 1200000,
    "preco_complemento": "Unidades limitadas",
    "status": "Últimas unidades",
    "previsao_entrega": "Jun/2026",
    "destaque": false,
    "whatsapp": "555135731139",
    "mensagem_whats": "Olá! Vi o lançamento Edifício Horizonte Premium no Portal de Investimento e gostaria de mais informações."
  },
  {
    "id": "lanc003",
    "titulo": "Condomínio Parque das Águas",
    "regiao": "Canoas",
    "agencia": "Canoas - Jardim do Lago",
    "tipo": "Casa em Condomínio",
    "imagem": "images/jardim do lago.jpg",
    "imagens": [
      "images/jardim do lago.jpg",
      "images/jardim do lago.jpg",
      "images/jardim do lago.jpg"
    ],
    "descricao": "Casas em condomínio fechado com completa infraestrutura, segurança 24h, área verde preservada e clube com piscinas.",
    "metragem": 140,
    "metragem_min": 120,
    "metragem_max": 180,
    "metragem_complemento": "Área construída",
    "quartos": 3,
    "quartos_min": 3,
    "quartos_max": 4,
    "quartos_complemento": "Suíte master",
    "banheiros": 3,
    "banheiros_complemento": "Suítes + lavabo",
    "vagas": 2,
    "vagas_complemento": "Garagem coberta",
    "sol": "Norte/Leste",
    "sol_complemento": "Ventilação cruzada",
    "preco": 680000,
    "preco_complemento": "Entrada facilitada",
    "status": "Lançamento",
    "previsao_entrega": "Mar/2027",
    "destaque": false,
    "whatsapp": "5551993303583",
    "mensagem_whats": "Olá! Vi o lançamento Condomínio Parque das Águas no Portal de Investimento e gostaria de mais informações."
  },
  {
    "id": "lanc004",
    "titulo": "Beach Living Residences",
    "regiao": "Santa Catarina",
    "agencia": "Porto Belo",
    "tipo": "Apartamento Vista Mar",
    "imagem": "images/sc.jpg",
    "imagens": [
      "images/sc.jpg",
      "images/sc.jpg",
      "images/sc.jpg"
    ],
    "descricao": "Viva frente ao mar! Apartamentos com vista deslumbrante, piscinas infinity, sauna e academia completa. Melhor localização da praia.",
    "metragem": 95,
    "metragem_min": 75,
    "metragem_max": 140,
    "metragem_complemento": "Com varanda gourmet",
    "quartos": 3,
    "quartos_min": 2,
    "quartos_max": 3,
    "quartos_complemento": "Suítes com vista",
    "banheiros": 2,
    "banheiros_complemento": "Alto padrão",
    "vagas": 2,
    "vagas_complemento": "Demarcadas",
    "sol": "Frente mar",
    "sol_complemento": "Vista privilegiada",
    "preco": 850000,
    "preco_complemento": "Valorização garantida",
    "status": "Pré-lançamento",
    "previsao_entrega": "Set/2026",
    "destaque": false,
    "whatsapp": "5551982628664",
    "mensagem_whats": "Olá! Vi o lançamento Beach Living Residences no Portal de Investimento e gostaria de mais informações."
  },
  {
    "id": "lanc005",
    "titulo": "Smart Office Boulevard",
    "regiao": "Porto Alegre",
    "agencia": "Moinhos de Vento",
    "tipo": "Sala Comercial",
    "imagem": "images/moinhos.jpg",
    "imagens": [
      "images/moinhos.jpg",
      "images/moinhos.jpg",
      "images/moinhos.jpg"
    ],
    "descricao": "Salas comerciais inteligentes em uma das principais avenidas de Porto Alegre. Infraestrutura completa, estacionamento amplo e localização estratégica.",
    "metragem": 45,
    "metragem_min": 35,
    "metragem_max": 85,
    "metragem_complemento": "Plantas flexíveis",
    "quartos": 0,
    "quartos_min": 0,
    "quartos_max": 0,
    "quartos_complemento": "Espaço corporativo",
    "banheiros": 1,
    "banheiros_complemento": "Por sala",
    "vagas": 1,
    "vagas_complemento": "Rotativas disponíveis",
    "sol": "Norte",
    "sol_complemento": "Ventilação natural",
    "preco": 320000,
    "preco_complemento": "Alto retorno",
    "status": "Em lançamento",
    "previsao_entrega": "Ago/2026",
    "destaque": false,
    "whatsapp": "555135731139",
    "mensagem_whats": "Olá! Vi o lançamento Smart Office Boulevard no Portal de Investimento e gostaria de mais informações."
  },
  {
    "id": "lanc006",
    "titulo": "Garden Residence Club",
    "regiao": "Santa Catarina",
    "agencia": "Santa Mônica - Florianópolis",
    "tipo": "Apartamento Garden",
    "imagem": "images/sc.jpg",
    "imagens": [
      "images/sc.jpg",
      "images/sc.jpg",
      "images/sc.jpg"
    ],
    "descricao": "Apartamentos garden com jardim privativo, churrasqueira e espaço pet. Condomínio completo com quadras, piscinas e área kids.",
    "metragem": 110,
    "metragem_min": 90,
    "metragem_max": 130,
    "metragem_complemento": "Mais jardim privativo",
    "quartos": 3,
    "quartos_min": 2,
    "quartos_max": 3,
    "quartos_complemento": "Com closet",
    "banheiros": 2,
    "banheiros_complemento": "Suítes",
    "vagas": 2,
    "vagas_complemento": "Paralelas",
    "sol": "Leste/Oeste",
    "sol_complemento": "Jardim amplo",
    "preco": 620000,
    "preco_complemento": "Condições especiais",
    "status": "Lançamento",
    "previsao_entrega": "Nov/2026",
    "destaque": false,
    "whatsapp": "5548988189757",
    "mensagem_whats": "Olá! Vi o lançamento Garden Residence Club no Portal de Investimento e gostaria de mais informações."
  }
]